gpt_code_scrapper/__init__.py
gpt_code_scrapper/scrapper.py
gpt_scrapper-1.0.dist-info/LICENSE
gpt_scrapper-1.0.dist-info/METADATA
gpt_scrapper-1.0.dist-info/WHEEL
gpt_scrapper-1.0.dist-info/entry_points.txt
gpt_scrapper-1.0.dist-info/top_level.txt
gpt_scrapper-1.0.dist-info/RECORD
