Metadata-Version: 2.1
Name: gpt-scrapper
Version: 1.0
Summary: Utility to scrap code from a directory, so GPT can tell you something about it
Home-page: https://github.com/danpeczek/gpt-scrapper
Author: danpeczek
License: MIT
Project-URL: Bug Tracker, https://github.com/danpeczek/gpt-scrapper/issues
Classifier: Environment :: Console
Classifier: Intended Audience :: Developers
Classifier: Operating System :: POSIX
Classifier: Programming Language :: Python
Classifier: Topic :: Communications :: Email
Classifier: Topic :: Software Development :: Bug Tracking
Classifier: License :: OSI Approved :: MIT License
Requires-Python: >=3.8
License-File: LICENSE
Requires-Dist: pyyaml
Requires-Dist: click
